pyconvcli/__init__.py
pyconvcli/app.py
pyconvcli/parse_classes.py
pyconvcli/pyconvcli.py
pyconvcli_internal_cli/__init__.py
pyconvcli_internal_cli/cli.py
pyconvcli_internal_cli/new.py
pyconvcli_internal_cli/pyconvcli.json
pyconvcli_internal_cli/resources/__init__.py
pyconvcli_internal_cli/resources/cli_class_template.txt
pyconvcli_internal_cli/resources/entry_class_template.txt
pyconvcli_internal_cli/resources/setup_template.txt
pyconvcli_internal_cli/utils/__init__.py
pyconvcli_internal_cli/utils/utils.py
test_pyconvcli_internal_cli/__init__.py
test_pyconvcli_internal_cli/cli.py
test_pyconvcli_internal_cli/test_pyconvcli.py
test_pyconvcli_internal_cli/test_resources/__init__.py
test_pyconvcli_internal_cli/test_resources/cli_class.py
pyconvcli-0.0.6.dist-info/LICENSE
pyconvcli-0.0.6.dist-info/METADATA
pyconvcli-0.0.6.dist-info/WHEEL
pyconvcli-0.0.6.dist-info/entry_points.txt
pyconvcli-0.0.6.dist-info/top_level.txt
pyconvcli-0.0.6.dist-info/RECORD
