Metadata-Version: 2.1
Name: pyconvcli
Version: 0.0.6
Summary: A convention based CLI framework for python
Home-page: https://github.com/jlepinski/pyconvcli
Author: Joshua Lepinski
Author-email: joshualepinski@gmail.com
License: UNKNOWN
Platform: UNKNOWN
Classifier: Programming Language :: Python :: 3
Classifier: License :: OSI Approved :: Apache Software License
Requires-Dist: pydash (==4.9.0)
Requires-Dist: stringcase (==1.2.0)
